pysarplus_cpp.cpython-38-x86_64-linux-gnu.so
pysarplus/__init__.py
pysarplus/SARPlus.py
pysarplus/SARModel.py
pysarplus/VERSION
pysarplus-0.6.6.dist-info/WHEEL
pysarplus-0.6.6.dist-info/RECORD
pysarplus-0.6.6.dist-info/METADATA
pysarplus-0.6.6.dist-info/top_level.txt
