Metadata-Version: 2.1
Name: pysarplus
Version: 0.6.6
Summary: SAR prediction for use with PySpark
Home-page: https://github.com/microsoft/recommenders/tree/main/contrib/sarplus
Author: RecoDev Team at Microsoft
Author-email: recodevteam@service.microsoft.com
License: MIT
Classifier: Development Status :: 5 - Production/Stable
Classifier: License :: OSI Approved :: MIT License
Classifier: Programming Language :: Python :: 3.6
Classifier: Programming Language :: Python :: 3.7
Classifier: Programming Language :: Python :: 3.8
Classifier: Programming Language :: Python :: 3.9
Classifier: Programming Language :: Python :: 3.10
Classifier: Intended Audience :: Developers
Classifier: Intended Audience :: Science/Research
Classifier: Topic :: Scientific/Engineering :: Mathematics
Requires-Python: >=3.6
Requires-Dist: numpy
Requires-Dist: pandas
Requires-Dist: pyarrow (>=1.0.0)
Requires-Dist: pybind11 (>=2.2)
Requires-Dist: pyspark (>=3.0.0)
